stocksera/__init__.py
stocksera/client.py
stocksera/exceptions.py
stocksera-0.1.21.dist-info/LICENSE
stocksera-0.1.21.dist-info/METADATA
stocksera-0.1.21.dist-info/WHEEL
stocksera-0.1.21.dist-info/top_level.txt
stocksera-0.1.21.dist-info/RECORD
