Metadata-Version: 2.1
Name: stocksera
Version: 0.1.21
Summary: Official Stocksera API
Home-page: https://github.com/guanquann/Stocksera-API
Author: Guan Quan
Author-email: stocksera@gmail.com.com
License: The MIT License (MIT)
Keywords: stocks,wallstreetbets,trading,senate,investing,finviz
Platform: UNKNOWN
Classifier: Programming Language :: Python :: 3.6
Classifier: Programming Language :: Python :: 3.7
Classifier: Programming Language :: Python :: 3.8
Classifier: Programming Language :: Python :: 3.9
Classifier: License :: OSI Approved :: MIT License
Requires-Python: >=3.6
License-File: LICENSE
